{"type":"Animation","props":{"y":0,"x":0,"width":92,"source":"bulletsSet/bullet7.atlas","presetID":1,"pivotY":46,"pivotX":46,"name":"bullet07","isPresetRoot":true,"interval":50,"height":240,"autoPlay":true},"compId":9,"child":[{"type":"Script","props":{"speed":4,"presetID":2,"isReportHit":true,"fishNetType":"FishNet01","fishNet":"@Prefab:prefab/fishNet01.prefab","bulletType":"Bullet07","bulletId":"Bullet07","runtime":"element/BulletControl.ts"},"compId":10}],"loadList":["prefab/fishNet01.prefab"],"loadList3D":[]}